hcore/__init__.py
hcore/hcore.cpython-36m-x86_64-linux-gnu.so
hcore/obj.cpython-36m-x86_64-linux-gnu.so
hcore-0.1.0.3.dist-info/DESCRIPTION.rst
hcore-0.1.0.3.dist-info/METADATA
hcore-0.1.0.3.dist-info/RECORD
hcore-0.1.0.3.dist-info/WHEEL
hcore-0.1.0.3.dist-info/metadata.json
hcore-0.1.0.3.dist-info/top_level.txt
