Metadata-Version: 2.0
Name: hcore
Version: 0.1.0.3
Summary: hcore
Home-page: https://pypi.org/user/gsmomo/
Author: zgs
Author-email: UNKNOWN
License: BSD License
Platform: all
Classifier: Operating System :: OS Independent
Classifier: Intended Audience :: Developers
Classifier: License :: OSI Approved :: BSD License
Classifier: Programming Language :: Python :: 3.6
Requires-Dist: Cython (>=0.29.5)
Requires-Dist: Werkzeug
